minty_infrastructure/__init__.py
minty_infrastructure/statsd.py
minty_infrastructure-0.0.2.dist-info/LICENSE
minty_infrastructure-0.0.2.dist-info/METADATA
minty_infrastructure-0.0.2.dist-info/WHEEL
minty_infrastructure-0.0.2.dist-info/top_level.txt
minty_infrastructure-0.0.2.dist-info/RECORD
