Metadata-Version: 2.1
Name: minty-infrastructure
Version: 0.0.2
Summary: Application Services for Zaaksysteem
Home-page: https://gitlab.com/minty-python/minty-infrastructure
Author: Martijn van de Streek
Author-email: martijn@mintlab.nl
License: EUPL license
Keywords: minty_infrastructure
Platform: UNKNOWN
Classifier: Development Status :: 2 - Pre-Alpha
Classifier: Intended Audience :: Developers
Classifier: License :: OSI Approved :: European Union Public Licence 1.2 (EUPL 1.2)
Classifier: Natural Language :: English
Classifier: Programming Language :: Python :: 3.6
Classifier: Programming Language :: Python :: 3.7
Requires-Dist: black
Requires-Dist: flake8
Requires-Dist: isort
Requires-Dist: sphinx
Requires-Dist: sphinx-rtd-theme
Requires-Dist: sphinx-autodoc-typehints
Requires-Dist: bumpversion
Requires-Dist: minty-config
Requires-Dist: statsd
